[
    {
        "author": "Smile Yik",
        "id": "Algorithms4th",
        "modifyTime": 0,
        "title": "Algorithms4th"
    },
    {
        "author": "Smile Yik",
        "id": "ComputerNetworking",
        "modifyTime": 0,
        "title": "ComputerNetworking"
    },
    {
        "author": "SmileYik",
        "id": "ita3th",
        "modifyTime": 1647099567337,
        "title": "算法导论学习"
    },
    {
        "author": "Smile Yik",
        "id": "csapp3th",
        "modifyTime": 1647099744269,
        "title": "深入理解计算机系统学习"
    }
]
